setup.py
gap_ex_forex_next3/__init__.py
gap_ex_forex_next3/gap_ex_forex_next3.py
gap_ex_forex_next3.egg-info/PKG-INFO
gap_ex_forex_next3.egg-info/SOURCES.txt
gap_ex_forex_next3.egg-info/dependency_links.txt
gap_ex_forex_next3.egg-info/not-zip-safe
gap_ex_forex_next3.egg-info/top_level.txt