Metadata-Version: 1.0
Name: gap-ex-forex-next3
Version: 1.22
Summary: gap_ex_forex_next3
Home-page: UNKNOWN
Author: omid
Author-email: UNKNOWN
License: UNKNOWN
Platform: UNKNOWN
